<?xml version="1.0" encoding="UTF-8"?>
<Ui xmlns="http://www.blizzard.com/wow/ui/" xmlns:xsi="http://www.w3.org/2001/XMLSchema-instance" xsi:schemaLocation="http://www.blizzard.com/wow/ui/">
	<!--
		Total RP 3
		Pet Browser

		Copyright 2014-2021 Total RP 3 Development Team

		Licensed under the Apache License, Version 2.0 (the "License");
		you may not use this file except in compliance with the License.
		You may obtain a copy of the License at

			http://www.apache.org/licenses/LICENSE-2.0

		Unless required by applicable law or agreed to in writing, software
		distributed under the License is distributed on an "AS IS" BASIS,
		WITHOUT WARRANTIES OR CONDITIONS OF ANY KIND, either express or implied.
		See the License for the specific language governing permissions and
		limitations under the License.
	-->
	<Script file="PetBrowser.lua"/>

	<CheckButton name="TRP3_PetBrowserIconButton" virtual="true">
		<Size x="37" y="37"/>
		<HitRectInsets left="-2" right="-2" top="-2" bottom="-2"/>
		<Layers>
			<Layer level="BORDER">
				<Texture parentKey="Icon" file="Interface\ICONS\INV_Misc_QuestionMark">
					<Anchors>
						<Anchor point="TOPLEFT" x="-2" y="2"/>
						<Anchor point="BOTTOMRIGHT" x="2" y="-2"/>
					</Anchors>
				</Texture>
				<MaskTexture parentKey="IconMask" file="Interface\Common\common-iconmask" hWrapMode="CLAMPTOBLACKADDITIVE" vWrapMode="CLAMPTOBLACKADDITIVE">
					<Anchors>
						<Anchor point="TOPLEFT" relativeKey="$parent.Icon" x="4" y="-4"/>
						<Anchor point="BOTTOMRIGHT" relativeKey="$parent.Icon" x="-4" y="4"/>
					</Anchors>
					<MaskedTextures>
						<MaskedTexture childKey="Icon"/>
					</MaskedTextures>
				</MaskTexture>
			</Layer>
			<Layer level="OVERLAY">
				<Texture parentKey="IconOverlay">
					<Anchors>
						<Anchor point="BOTTOMRIGHT" x="-2" y="2"/>
					</Anchors>
				</Texture>
			</Layer>
		</Layers>
		<NormalTexture file="Interface\Buttons\UI-Quickslot2">
			<Size x="60" y="60"/>
			<Anchors>
				<Anchor point="CENTER" y="-1"/>
			</Anchors>
		</NormalTexture>
		<PushedTexture file="Interface\Buttons\UI-Quickslot-Depress"/>
		<HighlightTexture atlas="WoWShare-Highlight">
			<Size x="35" y="35"/>
			<Anchors>
				<Anchor point="CENTER"/>
			</Anchors>
		</HighlightTexture>
		<CheckedTexture atlas="WoWShare-Selection">
			<Size x="35" y="35"/>
			<Anchors>
				<Anchor point="CENTER"/>
			</Anchors>
		</CheckedTexture>
		<Scripts>
			<OnClick>CallMethodOnNearestAncestor(self, "OnIconButtonClicked", self, self:GetID());</OnClick>
			<OnEnter>CallMethodOnNearestAncestor(self, "SetTooltipSlot", self:GetID());</OnEnter>
			<OnLeave>CallMethodOnNearestAncestor(self, "SetTooltipSlot", nil);</OnLeave>
		</Scripts>
	</CheckButton>

	<Frame name="TRP3_PetBrowserFrameTemplate" virtual="true" mixin="TRP3_PetBrowserMixin" enableMouse="true" toplevel="true" hidden="true">
		<KeyValues>
			<KeyValue key="layoutType" value="Dialog" type="string"/>
		</KeyValues>
		<Size x="425" y="400"/>
		<Anchors>
			<Anchor point="CENTER"/>
		</Anchors>
		<Layers>
			<Layer level="BACKGROUND">
				<Texture parentKey="Background" atlas="Headhunter_BG">
					<Anchors>
						<Anchor point="TOPLEFT" x="10" y="-10"/>
						<Anchor point="BOTTOMRIGHT" x="-10" y="10"/>
					</Anchors>
				</Texture>
			</Layer>
		</Layers>
		<Frames>
			<Frame parentKey="NineSlice" inherits="NineSlicePanelTemplate" useParentLevel="true"/>
			<Frame parentKey="Header">
				<Size x="260" y="58"/>
				<Anchors>
					<Anchor point="TOP" y="-11"/>
				</Anchors>
				<Layers>
					<!-- Sublevel 2 overlays the texture atop the inset shadow on the model frame. -->
					<Layer level="ARTWORK" textureSubLevel="2">
						<Texture parentKey="Background" atlas="storyheader-bg" useAtlasSize="true"/>
					</Layer>
					<Layer level="OVERLAY">
						<FontString parentKey="Text" inherits="QuestTitleFontBlackShadow" justifyH="CENTER" justifyV="MIDDLE">
							<Anchors>
								<Anchor point="TOPLEFT" relativeKey="$parent.Header"/>
								<Anchor point="BOTTOMRIGHT" relativeKey="$parent.Header" y="8"/>
							</Anchors>
						</FontString>
					</Layer>
				</Layers>
			</Frame>
			<Frame parentKey="IconPager">
				<Anchors>
					<Anchor point="TOPLEFT" relativePoint="LEFT" x="55" y="-47"/>
					<Anchor point="BOTTOMRIGHT" x="-54" y="51"/>
				</Anchors>
				<Layers>
					<Layer level="BACKGROUND">
						<Texture parentKey="Background" atlas="creditsscreen-background-8" horizTile="true" vertTile="true"/>
					</Layer>
					<Layer level="OVERLAY" textureSubLevel="7">
						<Texture parentKey="Divider" atlas="questlog_divider" useAtlasSize="true">
							<Anchors>
								<Anchor point="LEFT" relativePoint="TOPLEFT" y="4"/>
								<Anchor point="RIGHT" relativePoint="TOPRIGHT"/>
							</Anchors>
						</Texture>
					</Layer>
				</Layers>
				<Frames>
					<Button parentKey="PrevPageButton">
						<Size x="32" y="32"/>
						<Anchors>
							<Anchor point="LEFT" x="16"/>
						</Anchors>
						<NormalTexture file="Interface\Buttons\UI-SpellbookIcon-PrevPage-Up"/>
						<PushedTexture file="Interface\Buttons\UI-SpellbookIcon-PrevPage-Down"/>
						<DisabledTexture file="Interface\Buttons\UI-SpellbookIcon-PrevPage-Disabled"/>
						<HighlightTexture file="Interface\Buttons\UI-Common-MouseHilight" alphaMode="ADD"/>
						<Scripts>
							<OnClick>CallMethodOnNearestAncestor(self, "OnPrevPageButtonClicked");</OnClick>
						</Scripts>
					</Button>
					<Button parentKey="NextPageButton">
						<Size x="32" y="32"/>
						<Anchors>
							<Anchor point="RIGHT" x="-16"/>
						</Anchors>
						<NormalTexture file="Interface\Buttons\UI-SpellbookIcon-NextPage-Up"/>
						<PushedTexture file="Interface\Buttons\UI-SpellbookIcon-NextPage-Down"/>
						<DisabledTexture file="Interface\Buttons\UI-SpellbookIcon-NextPage-Disabled"/>
						<HighlightTexture file="Interface\Buttons\UI-Common-MouseHilight" alphaMode="ADD"/>
						<Scripts>
							<OnClick>CallMethodOnNearestAncestor(self, "OnNextPageButtonClicked");</OnClick>
						</Scripts>
					</Button>
				</Frames>
			</Frame>
			<PlayerModel parentKey="Model" inherits="ModelWithZoomTemplate" mixin="PetStableModelFrameMixin">
				<Anchors>
					<Anchor point="TOP" relativeKey="$parent.Header" relativePoint="BOTTOM" y="18"/>
					<Anchor point="BOTTOM" relativeKey="$parent.IconPager" relativePoint="TOP"/>
					<Anchor point="RIGHT" relativeKey="$parent.IconPager" x="-1"/>
					<Anchor point="LEFT" relativeKey="$parent.IconPager"/>
				</Anchors>
				<Layers>
					<!-- Sublevel 1 overlays the texture atop the model. -->
					<Layer level="ARTWORK" textureSubLevel="1">
						<Texture parentKey="InsetShadow" atlas="insetshadow">
							<Anchors>
								<Anchor point="TOPLEFT" x="0" y="0"/>
								<Anchor point="BOTTOMRIGHT" x="1" y="-1"/>
							</Anchors>
						</Texture>
					</Layer>
					<Layer level="OVERLAY">
						<FontString parentKey="OverlayText" inherits="GameFontNormal">
							<Anchors>
								<Anchor point="TOPLEFT" x="16" y="16"/>
								<Anchor point="BOTTOMRIGHT" x="-16" y="-16"/>
							</Anchors>
						</FontString>
					</Layer>
				</Layers>
			</PlayerModel>
			<Button parentKey="AcceptButton" inherits="SharedButtonTemplate">
				<Size x="120" y="23"/>
				<Anchors>
					<Anchor point="BOTTOM" y="20"/>
				</Anchors>
				<Scripts>
					<OnClick>CallMethodOnNearestAncestor(self, "Accept");</OnClick>
				</Scripts>
			</Button>
			<Button parentKey="CloseButton" inherits="UIPanelCloseButtonNoScripts">
				<Anchors>
					<Anchor point="TOPRIGHT" x="-8" y="-8"/>
				</Anchors>
				<Scripts>
					<OnClick>CallMethodOnNearestAncestor(self, "Cancel");</OnClick>
				</Scripts>
			</Button>
		</Frames>
		<Scripts>
			<OnLoad method="OnLoad"/>
			<OnEvent method="OnEvent"/>
			<OnShow method="OnShow"/>
			<OnHide method="OnHide"/>
			<OnMouseWheel method="OnMouseWheel"/>
			<OnMouseUp method="OnMouseUp"/>
		</Scripts>
	</Frame>
</Ui>
